test/test.py
utilskit/__init__.py
utilskit/classificationutils/__init__.py
utilskit/classificationutils/classificationutils.py
utilskit/dataframeutils/__init__.py
utilskit/dataframeutils/dataframeutils.py
utilskit/dbutils/__init__.py
utilskit/dbutils/dbutils.py
utilskit/plotutils/__init__.py
utilskit/plotutils/plotutils.py
utilskit/repeatutils/__init__.py
utilskit/repeatutils/repeatutils.py
utilskit/timeutils/__init__.py
utilskit/timeutils/timeutils.py
utilskit/utils/__init__.py
utilskit/utils/utils.py
utilskit-0.2.17.dist-info/METADATA
utilskit-0.2.17.dist-info/WHEEL
utilskit-0.2.17.dist-info/top_level.txt
utilskit-0.2.17.dist-info/RECORD
