Metadata-Version: 2.4
Name: utilskit
Version: 0.2.17
Summary: 다양한 편의성 함수 모음 패키지
Author-email: kimyh <kim_yh663927@naver.com>
Classifier: Programming Language :: Python :: 3
Classifier: License :: OSI Approved :: MIT License
Classifier: Operating System :: OS Independent
Requires-Python: >=3.10
Requires-Dist: matplotlib==3.10.3
Requires-Dist: numpy==2.2.6
Requires-Dist: pandas==2.3.1
Requires-Dist: PyMySQL==1.1.1
Requires-Dist: SQLAlchemy==2.0.41
Requires-Dist: tqdm==4.67.1
Requires-Dist: xlrd==2.0.2
Requires-Dist: openpyxl==3.1.5
